pycafe_server/__about__.py
pycafe_server/__init__.py
pycafe_server/asgi.py
pycafe_server/auth.py
pycafe_server/config.py
pycafe_server/cookie.py
pycafe_server/database.py
pycafe_server/license.py
pycafe_server/request_proxy.py
pycafe_server/session.py
pycafe_server/sign.py
pycafe_server/uv_util.py
pycafe_server/client/__init__.py
pycafe_server/client/file-template.html
pycafe_server/client/requirements_system.py
pycafe_server/client/shared.py
pycafe_server/static/404.html
pycafe_server/static/admin.html
pycafe_server/static/admin.txt
pycafe_server/static/api-keys.html
pycafe_server/static/api-keys.txt
pycafe_server/static/app.py
pycafe_server/static/badge.svg
pycafe_server/static/bootstrap_jupyter_kernel.py
pycafe_server/static/coffeecup.gif
pycafe_server/static/dash_daq-0.5.0-py3-none-any.whl
pycafe_server/static/favicon.ico
pycafe_server/static/fs-worker.js
pycafe_server/static/fs-worker.js.LICENSE.txt
pycafe_server/static/google_crc32c-1.5.0-py3-none-any.whl
pycafe_server/static/index.html
pycafe_server/static/index.txt
pycafe_server/static/ipykernel-6.9.2-py3-none-any.whl
pycafe_server/static/jupyterlite_pyodide_kernel-0.0.8-py3-none-any.whl
pycafe_server/static/logo.png
pycafe_server/static/next.svg
pycafe_server/static/pyodide_kernel-0.0.8-py3-none-any.whl
pycafe_server/static/pyperclip-1.8.2-py3-none-any.whl
pycafe_server/static/qr_buy_eu.png
pycafe_server/static/qr_buy_us.png
pycafe_server/static/requirements.txt
pycafe_server/static/service-worker.js
pycafe_server/static/sign-in.html
pycafe_server/static/sign-in.txt
pycafe_server/static/stringcase-1.2.0-py3-none-any.whl
pycafe_server/static/test_dash.py
pycafe_server/static/test_ipykernel.py
pycafe_server/static/test_jupyterlab.py
pycafe_server/static/test_solara.py
pycafe_server/static/test_starlette.py
pycafe_server/static/test_streamlit.py
pycafe_server/static/test_tornado.py
pycafe_server/static/tor.py
pycafe_server/static/tornado-6.4.2-py3-none-any.whl
pycafe_server/static/vercel.svg
pycafe_server-0.8.2.dist-info/METADATA
pycafe_server-0.8.2.dist-info/WHEEL
pycafe_server-0.8.2.dist-info/entry_points.txt
pycafe_server-0.8.2.dist-info/licenses/LICENSE.txt
pycafe_server-0.8.2.dist-info/RECORD
