Metadata-Version: 2.4
Name: pycafe-server
Version: 0.8.2
Summary: Run your own PyCafe server on on-premises
Project-URL: Documentation, https://py.cafe/docs/self-hosted
Project-URL: Issues, https://py.cafe/docs/self-hosted
Author-email: "Maarten A. Breddels" <maartenbreddels@gmail.com>
License: Not open source, contact contact@py.cafe for licencing.
License-File: LICENSE.txt
Classifier: License :: Other/Proprietary License
Classifier: Programming Language :: Python
Classifier: Programming Language :: Python :: 3.7
Classifier: Programming Language :: Python :: 3.8
Classifier: Programming Language :: Python :: 3.9
Classifier: Programming Language :: Python :: 3.10
Classifier: Programming Language :: Python :: 3.11
Classifier: Programming Language :: Python :: Implementation :: CPython
Classifier: Programming Language :: Python :: Implementation :: PyPy
Requires-Python: >=3.7
Requires-Dist: authlib
Requires-Dist: bump2version
Requires-Dist: httpx
Requires-Dist: itsdangerous
Requires-Dist: packaging
Requires-Dist: pyjwt
Requires-Dist: python-multipart
Requires-Dist: requests
Requires-Dist: sqlalchemy>=2
Requires-Dist: starlette
Requires-Dist: uv<0.8,>=0.3.5
Requires-Dist: uvicorn
